llm/__init__.py
llm/chatllm.py
llm/qa.py
llm/utils.py
llm/applications/Question2Answer.py
llm/applications/__init__.py
llm/applications/ann4qa.py
llm/applications/chat.py
llm/applications/chatpdf.py
llm/applications/crawler4qa.py
llm/applications/pipeline.py
llm/clis/README.md
llm/clis/__init__.py
llm/clis/cli.py
llm/docutils/__init__.py
llm/docutils/doc_embedding.py
llm/docutils/doc_parse.py
llm/kb/FaissANN.py
llm/kb/__init__.py
llm/kb/kbqa.py
llm/knowledge_base/__init__.py
llm/knowledge_base/lite.py
llm/textsplitter/__init__.py
llm/textsplitter/chinese_text_splitter.py
llm/uis/__init__.py
llm/uis/gradio_ui.py
llm4chat-2023.4.24.19.22.24.dist-info/AUTHORS.rst
llm4chat-2023.4.24.19.22.24.dist-info/LICENSE
llm4chat-2023.4.24.19.22.24.dist-info/METADATA
llm4chat-2023.4.24.19.22.24.dist-info/WHEEL
llm4chat-2023.4.24.19.22.24.dist-info/entry_points.txt
llm4chat-2023.4.24.19.22.24.dist-info/top_level.txt
llm4chat-2023.4.24.19.22.24.dist-info/RECORD
